phgeograpy/__init__.py
phgeograpy/__version__.py
phgeograpy/data/__init__.py
phgeograpy/data/regions/__init__.py
phgeograpy/data/regions/armm.py
phgeograpy/data/regions/car.py
phgeograpy/data/regions/mimaropa.py
phgeograpy/data/regions/ncr.py
phgeograpy/data/regions/region1.py
phgeograpy/data/regions/region10.py
phgeograpy/data/regions/region11.py
phgeograpy/data/regions/region12.py
phgeograpy/data/regions/region13.py
phgeograpy/data/regions/region2.py
phgeograpy/data/regions/region3.py
phgeograpy/data/regions/region4a.py
phgeograpy/data/regions/region5.py
phgeograpy/data/regions/region6.py
phgeograpy/data/regions/region7.py
phgeograpy/data/regions/region8.py
phgeograpy/data/regions/region9.py
phgeograpy-1.0.0.dist-info/DESCRIPTION.rst
phgeograpy-1.0.0.dist-info/METADATA
phgeograpy-1.0.0.dist-info/RECORD
phgeograpy-1.0.0.dist-info/WHEEL
phgeograpy-1.0.0.dist-info/metadata.json
phgeograpy-1.0.0.dist-info/top_level.txt
