Metadata-Version: 2.0
Name: phgeograpy
Version: 1.0.0
Summary: A python package that lists regions, provinces, and cities/municipalities in the Philippines
Home-page: https://github.com/drfb/phgeograpy
Author: Dhan-Rheb Belza
Author-email: dhanrheb@gmail.com
License: MIT
Keywords: philippine geography regions provinces cities municipalities
Platform: UNKNOWN
Classifier: Intended Audience :: Developers
Classifier: License :: OSI Approved :: MIT License
Classifier: Operating System :: OS Independent
Classifier: Programming Language :: Python :: 2
Classifier: Programming Language :: Python :: 2.7
Classifier: Programming Language :: Python :: 3
Classifier: Programming Language :: Python :: 3.6
Classifier: Topic :: Software Development :: Libraries :: Python Modules
